odoo/addons/ssi_account_receivable_penalty/README.rst
odoo/addons/ssi_account_receivable_penalty/__init__.py
odoo/addons/ssi_account_receivable_penalty/__manifest__.py
odoo/addons/ssi_account_receivable_penalty/approval_template/batch_receivable_penalty_computation.xml
odoo/addons/ssi_account_receivable_penalty/data/account_journal_data.xml
odoo/addons/ssi_account_receivable_penalty/data/approval_template_data.xml
odoo/addons/ssi_account_receivable_penalty/data/base_automation_data.xml
odoo/addons/ssi_account_receivable_penalty/data/ir_actions_server_data.xml
odoo/addons/ssi_account_receivable_penalty/data/ir_sequence_data.xml
odoo/addons/ssi_account_receivable_penalty/data/receivable_penalty_comp_policy_data.xml
odoo/addons/ssi_account_receivable_penalty/data/receivable_penalty_policy_data.xml
odoo/addons/ssi_account_receivable_penalty/data/sequence_template_data.xml
odoo/addons/ssi_account_receivable_penalty/demo/account_account_demo.xml
odoo/addons/ssi_account_receivable_penalty/demo/account_journal_demo.xml
odoo/addons/ssi_account_receivable_penalty/demo/account_receivable_penalty_type_demo.xml
odoo/addons/ssi_account_receivable_penalty/i18n/ssi_account_receivable_penalty.pot
odoo/addons/ssi_account_receivable_penalty/ir_model_access/batch_receivable_penalty_computation.xml
odoo/addons/ssi_account_receivable_penalty/ir_model_access/batch_receivable_penalty_computation_detail.xml
odoo/addons/ssi_account_receivable_penalty/ir_module_category/batch_receivable_penalty_computation.xml
odoo/addons/ssi_account_receivable_penalty/ir_rule/batch_receivable_penalty_computation.xml
odoo/addons/ssi_account_receivable_penalty/ir_sequence/batch_receivable_penalty_computation.xml
odoo/addons/ssi_account_receivable_penalty/models/__init__.py
odoo/addons/ssi_account_receivable_penalty/models/account_move.py
odoo/addons/ssi_account_receivable_penalty/models/account_move_line.py
odoo/addons/ssi_account_receivable_penalty/models/account_receivable_penalty.py
odoo14_addon_ssi_account_receivable_penalty-14.0.3.8.0.dist-info/METADATA
odoo14_addon_ssi_account_receivable_penalty-14.0.3.8.0.dist-info/WHEEL
odoo14_addon_ssi_account_receivable_penalty-14.0.3.8.0.dist-info/top_level.txt
odoo14_addon_ssi_account_receivable_penalty-14.0.3.8.0.dist-info/RECORD
